pycountdict/__init__.py
pycountdict-1.0.4.dist-info/LICENSE
pycountdict-1.0.4.dist-info/METADATA
pycountdict-1.0.4.dist-info/WHEEL
pycountdict-1.0.4.dist-info/top_level.txt
pycountdict-1.0.4.dist-info/RECORD
