Metadata-Version: 2.1
Name: pycountdict
Version: 1.0.4
Summary: python counter dictionary
Home-page: https://github.com/bjtj/python-counter-dictionary
Author: bjtj
Author-email: bjtj10@gmail.com
License: UNKNOWN
Platform: UNKNOWN
Classifier: Programming Language :: Python :: 3
Classifier: License :: OSI Approved :: MIT License
Classifier: Operating System :: OS Independent
